wptools/PhpVariableExtractor.py
wptools/__init__.py
wordpresstools-0.0.3.dist-info/LICENSE
wordpresstools-0.0.3.dist-info/METADATA
wordpresstools-0.0.3.dist-info/WHEEL
wordpresstools-0.0.3.dist-info/top_level.txt
wordpresstools-0.0.3.dist-info/RECORD
